setup.cfg
setup.py
cxg/__init__.py
cxg.egg-info/PKG-INFO
cxg.egg-info/SOURCES.txt
cxg.egg-info/dependency_links.txt
cxg.egg-info/top_level.txt