Metadata-Version: 1.1
Name: cxg
Version: 0.20161121
Summary: Construction grammar engine, supporing scone-server interaction
Home-page: https://bitbucket.org/DavidVilla/python-cxg
Author: David Villa Alises
Author-email: David.Villa@gmail.com
License: GPLv3
Platform: UNKNOWN
Classifier: Intended Audience :: Developers
Classifier: License :: OSI Approved :: GNU General Public License v3 or later (GPLv3+)
Classifier: Operating System :: OS Independent
Classifier: Programming Language :: Python :: 3
Classifier: Programming Language :: Python :: 3.0
Classifier: Programming Language :: Python :: 3.1
Classifier: Programming Language :: Python :: 3.2
Classifier: Programming Language :: Python :: 3.3
Classifier: Programming Language :: Python :: 3.4
Classifier: Programming Language :: Python :: 3.5
Provides: cxg
